statick_rosm_registry-0.1.1.dist-info/DESCRIPTION.rst
statick_rosm_registry-0.1.1.dist-info/METADATA
statick_rosm_registry-0.1.1.dist-info/RECORD
statick_rosm_registry-0.1.1.dist-info/WHEEL
statick_rosm_registry-0.1.1.dist-info/metadata.json
statick_rosm_registry-0.1.1.dist-info/top_level.txt
statick_tool/plugins/reporting/rosm_registry_plugin/__init__.py
statick_tool/plugins/reporting/rosm_registry_plugin/json_risk_assessment_reporting_plugin.py
statick_tool/plugins/reporting/rosm_registry_plugin/json_risk_assessment_reporting_plugin.yapsy-plugin
statick_tool/plugins/reporting/rosm_registry_plugin/risk_analyzer.py
statick_tool/rsc/cert_severity_likelihood.txt
