Metadata-Version: 2.0
Name: statick-rosm-registry
Version: 0.1.1
Summary: Statick extension to generate files for the ROS-M registry.
Home-page: https://github.com/soartech/statick-rosm-registry
Author: Soar Technology, Inc.
License: UNKNOWN
Platform: UNKNOWN
Classifier: License :: OSI Approved :: BSD License
Classifier: Programming Language :: Python :: 2.7
Classifier: Programming Language :: Python :: 3.4
Classifier: Programming Language :: Python :: 3.5
Classifier: Programming Language :: Python :: 3.6
Classifier: Programming Language :: Python :: 3.7
Classifier: Topic :: Software Development :: Testing
Provides-Extra: test
Requires-Dist: statick
Provides-Extra: test
Requires-Dist: pytest; extra == 'test'
